odoo9_addon_account_invoice_refund_link-9.0.2.0.2-py2.7-nspkg.pth
odoo9_addon_account_invoice_refund_link-9.0.2.0.2.dist-info/DESCRIPTION.rst
odoo9_addon_account_invoice_refund_link-9.0.2.0.2.dist-info/METADATA
odoo9_addon_account_invoice_refund_link-9.0.2.0.2.dist-info/RECORD
odoo9_addon_account_invoice_refund_link-9.0.2.0.2.dist-info/WHEEL
odoo9_addon_account_invoice_refund_link-9.0.2.0.2.dist-info/metadata.json
odoo9_addon_account_invoice_refund_link-9.0.2.0.2.dist-info/namespace_packages.txt
odoo9_addon_account_invoice_refund_link-9.0.2.0.2.dist-info/top_level.txt
odoo_addons/account_invoice_refund_link/README.rst
odoo_addons/account_invoice_refund_link/__init__.py
odoo_addons/account_invoice_refund_link/__openerp__.py
odoo_addons/account_invoice_refund_link/hooks.py
odoo_addons/account_invoice_refund_link/i18n/ar.po
odoo_addons/account_invoice_refund_link/i18n/bg.po
odoo_addons/account_invoice_refund_link/i18n/bs.po
odoo_addons/account_invoice_refund_link/i18n/ca.po
odoo_addons/account_invoice_refund_link/i18n/ca_ES.po
odoo_addons/account_invoice_refund_link/i18n/cs.po
odoo_addons/account_invoice_refund_link/i18n/da.po
odoo_addons/account_invoice_refund_link/i18n/de.po
odoo_addons/account_invoice_refund_link/i18n/el_GR.po
odoo_addons/account_invoice_refund_link/i18n/en_GB.po
odoo_addons/account_invoice_refund_link/i18n/es.po
odoo_addons/account_invoice_refund_link/i18n/es_AR.po
odoo_addons/account_invoice_refund_link/i18n/es_BO.po
odoo_addons/account_invoice_refund_link/i18n/es_CL.po
odoo_addons/account_invoice_refund_link/i18n/es_CO.po
odoo_addons/account_invoice_refund_link/i18n/es_CR.po
odoo_addons/account_invoice_refund_link/i18n/es_DO.po
odoo_addons/account_invoice_refund_link/i18n/es_EC.po
odoo_addons/account_invoice_refund_link/i18n/es_ES.po
odoo_addons/account_invoice_refund_link/i18n/es_MX.po
odoo_addons/account_invoice_refund_link/i18n/es_PE.po
odoo_addons/account_invoice_refund_link/i18n/es_PY.po
odoo_addons/account_invoice_refund_link/i18n/es_VE.po
odoo_addons/account_invoice_refund_link/i18n/et.po
odoo_addons/account_invoice_refund_link/i18n/eu.po
odoo_addons/account_invoice_refund_link/i18n/eu_ES.po
odoo_addons/account_invoice_refund_link/i18n/fa.po
odoo_addons/account_invoice_refund_link/i18n/fi.po
odoo_addons/account_invoice_refund_link/i18n/fr.po
odoo_addons/account_invoice_refund_link/i18n/fr_CA.po
odoo_addons/account_invoice_refund_link/i18n/fr_CH.po
odoo_addons/account_invoice_refund_link/i18n/fr_FR.po
