Metadata-Version: 2.0
Name: odoo9-addon-account-invoice-refund-link
Version: 9.0.2.0.2
Summary: Link refund invoice with its original invoice
Home-page: https://odoo-community.org/
Author: Pexego, Tecnativa, Odoo Community Association (OCA)
Author-email: support@odoo-community.org
License: AGPL-3
Platform: UNKNOWN
Classifier: Programming Language :: Python
Classifier: Framework :: Odoo
Classifier: License :: OSI Approved :: GNU Affero General Public License v3
Requires-Python: ~=2.7
Requires-Dist: odoo (<9.1a,>=9.0a)
